pycellmech/__init__.py
pycellmech/cli.py
pycellmech/geometric_shape_features.py
pycellmech/main.py
pycellmech/one_dimensional_features.py
pycellmech/polygonal_shape_features.py
pycellmech_create_label/__init__.py
pycellmech_create_label/cli.py
pycellmech_create_label/main.py
pycellmech_nifti/__init__.py
pycellmech_nifti/cli.py
pycellmech_nifti/main.py
pycellmech-2.1.12.dist-info/LICENSE.txt
pycellmech-2.1.12.dist-info/METADATA
pycellmech-2.1.12.dist-info/NOTICE.txt
pycellmech-2.1.12.dist-info/WHEEL
pycellmech-2.1.12.dist-info/entry_points.txt
pycellmech-2.1.12.dist-info/top_level.txt
pycellmech-2.1.12.dist-info/RECORD
