Metadata-Version: 2.1
Name: pycellmech
Version: 2.1.12
Summary: A shape-based feature extractor for use in biological and medical studies.
Home-page: https://github.com/icm-dac/pycellmech
Author: Janan Arslan
Author-email: janan.arslan@icm-institute.org
License: UNKNOWN
Platform: UNKNOWN
Classifier: Programming Language :: Python :: 3
Classifier: License :: Other/Proprietary License
Classifier: Operating System :: OS Independent
Requires-Python: >=3.6
Requires-Dist: matplotlib
Requires-Dist: numpy
Requires-Dist: opencv-python
Requires-Dist: pandas
Requires-Dist: scikit-learn
Requires-Dist: SimpleITK
Requires-Dist: scikit-image
